{
  "schemaVersion": "2026-05-27",
  "claimBoundary": "desktop WebXR comparator blocker report only; not Quest, production, clinical, or scoring readiness",
  "currentGrade": "B",
  "currentScore": 84,
  "targetGrade": "B+",
  "screenshot": "docs/openclinxr/screenshots/ui-xr-ob-humanoid-source-charmorph-reom-face-pose-2026-05-27.png",
  "blockers": [
    {
      "id": "fitted_cloth_not_planar",
      "severity": "high",
      "currentFinding": "Current Reom garment still reads as planar/apron-like in WebXR source-clean screenshot.",
      "remediation": "Source or create a real garment mesh and pass it through local Blender fitter with shrinkwrap/weight transfer; do not replace baseline unless screenshot score improves."
    },
    {
      "id": "forearm_hand_rest_pose",
      "severity": "medium",
      "currentFinding": "Arms improved from T-pose but forearms/hands remain stiff and mannequin-like.",
      "remediation": "Tune patient joint rotations and capture before/after WebXR-only screenshots."
    },
    {
      "id": "hair_face_material_detail",
      "severity": "medium",
      "currentFinding": "Face/hair surface remains low-detail and mannequin-like, limiting realism even after clothing cleanup.",
      "remediation": "Add source-level material/texture detail or provider comparison for face/hair candidates."
    },
    {
      "id": "source_clean_crop",
      "severity": "done",
      "currentFinding": "Comparator now crops to WebXR pane and hides debug panels/cues.",
      "remediation": "Preserve this behavior for future screenshots."
    }
  ],
  "topRemediationSlice": "real_garment_mesh_source_allowlist_or_local_authored_mesh_then_fit_to_reom",
  "nextQueueItem": "Improve local garment generator/fitter side-wrap geometry and rerun comparator.",
  "latestLocalAuthoredCandidate": {
    "id": "reom_local_authored_curved_garment_patient",
    "screenshot": "docs/openclinxr/screenshots/ui-xr-ob-humanoid-source-reom-local-authored-curved-garment-face-pose-2026-05-27.png",
    "result": "does_not_beat_B84_baseline",
    "finding": "local-authored curved garment remains planar/apron-like after fitting; do not promote over baseline",
    "nextRemediation": "improve fitter/generator to produce side/back wrapped torso geometry with better placement and less rectangular front panel"
  }
}
