{"url":"http://127.0.0.1:5173/?scenarioId=ob_headache_preeclampsia_triage_v1&examSequence=ed_chest_pain_priority_v1%2Cob_headache_preeclampsia_triage_v1&examEncounterSeconds=3&examNoteSeconds=3&capture=exam-flow-evidence","evidence":{"source":"local_exam_flow_runtime","scenarioId":"ob_headache_preeclampsia_triage_v1","scenarioIndex":1,"totalScenarios":2,"nextScenarioId":null,"phase":"encounter","encounterDurationSeconds":3,"noteDurationSeconds":3,"encounterElapsedSeconds":9,"noteElapsedSeconds":0,"encounterRemainingSeconds":0,"noteRemainingSeconds":3,"noteTextLength":0,"noteSubmitted":false,"canAdvanceToNextEncounter":false,"lastAdvanceReason":null,"acceleratedByQuery":true},"selectedBundle":"local_exam_run:ob_headache_preeclampsia_triage_encounter_v1:generated-runtime-assets","title":"OB Headache Preeclampsia Triage","noteValue":""}